BetterJSONStorage/BetterJSONStorage.py
BetterJSONStorage/__init__.py
BetterJSONStorage-1.3.2.dist-info/LICENSE.txt
BetterJSONStorage-1.3.2.dist-info/METADATA
BetterJSONStorage-1.3.2.dist-info/WHEEL
BetterJSONStorage-1.3.2.dist-info/top_level.txt
BetterJSONStorage-1.3.2.dist-info/RECORD
