Metadata-Version: 2.1
Name: BetterJSONStorage
Version: 1.3.2
Summary: An optimized tinyDB storage extension
Home-page: https://github.com/MrPigss/BetterJSONStorage
Author: Thomas Eeckhout
Author-email: Thomas Eeckhout <Thomas.Eeckhout@outlook.be>
License: MIT License
Project-URL: Homepage, https://github.com/MrPigss/BetterJSONStorage
Classifier: Operating System :: OS Independent
Classifier: Programming Language :: Python :: 3
Classifier: Topic :: Database
Requires-Python: >=3.8
License-File: LICENSE.txt
Requires-Dist: blosc2
Requires-Dist: mypy
Requires-Dist: orjson
Requires-Dist: tinydb
